{
    "id": "mapped_orders.csv",
    "name": "mapped_orders.csv",
    "description": null,
    "sourceColumns": [
        {
            "id": "HN1239",
            "hNodeId": "HN1239",
            "columnName": "encoutner_reg_uri_string"
        },
        {
            "id": "HN12",
            "hNodeId": "HN12",
            "columnName": "RAWTOHEX.FK_PATIENT_ENCOUNTER_ID."
        },
        {
            "id": "HN1135",
            "hNodeId": "HN1135",
            "columnName": "enc_uri"
        },
        {
            "id": "HN14",
            "hNodeId": "HN14",
            "columnName": "ORDER_NAME"
        },
        {
            "id": "HN13",
            "hNodeId": "HN13",
            "columnName": "PK_ORDER_MED_ID"
        },
        {
            "id": "HN1031",
            "hNodeId": "HN1031",
            "columnName": "prescription_uri"
        },
        {
            "id": "HN17",
            "hNodeId": "HN17",
            "columnName": "d.full_s"
        }
    ],
    "mappingToSourceColumns": [
        {
            "id": "HN1239",
            "sourceColumnId": "HN1239"
        },
        {
            "id": "HN12",
            "sourceColumnId": "HN12"
        },
        {
            "id": "HN1135",
            "sourceColumnId": "HN1135"
        },
        {
            "id": "HN14",
            "sourceColumnId": "HN14"
        },
        {
            "id": "HN13",
            "sourceColumnId": "HN13"
        },
        {
            "id": "HN1031",
            "sourceColumnId": "HN1031"
        },
        {
            "id": "HN17",
            "sourceColumnId": "HN17"
        }
    ],
    "graph": {
        "nodes": [
            {
                "id": "http://purl.obolibrary.org/obo/OGMS_00000971",
                "label": {
                    "uri": "http://purl.obolibrary.org/obo/OGMS_0000097",
                    "rdfsLabel": "health care encounter"
                },
                "type": "InternalNode",
                "modelIds": null
            },
            {
                "id": "http://purl.obolibrary.org/obo/PDRO_00000241",
                "label": {
                    "uri": "http://purl.obolibrary.org/obo/PDRO_0000024",
                    "rdfsLabel": "drug prescription"
                },
                "type": "InternalNode",
                "modelIds": null
            },
            {
                "id": "HN1239",
                "label": {
                    "uri": "HN1239",
                    "rdfsLabel": null
                },
                "type": "ColumnNode",
                "hNodeId": "HN1239",
                "columnName": "encoutner_reg_uri_string",
                "rdfLiteralType": {
                    "uri": "http://www.w3.org/2001/XMLSchema#anyURI",
                    "rdfsLabel": null
                },
                "language": "",
                "userSemanticTypes": [
                    {
                        "hNodeId": "HN1239",
                        "domain": {
                            "uri": "http://purl.obolibrary.org/obo/OGMS_0000097",
                            "rdfsLabel": "health care encounter"
                        },
                        "type": {
                            "uri": "http://transformunify.org/ontologies/TURBO_0000650",
                            "rdfsLabel": "shortcut health care encounter to encounter identifier registry URI string"
                        },
                        "origin": "User",
                        "confidenceScore": 1.0
                    },
                    {
                        "hNodeId": "HN1239",
                        "domain": {
                            "uri": "http://purl.obolibrary.org/obo/OGMS_0000097",
                            "rdfsLabel": "health care encounter"
                        },
                        "type": {
                            "uri": "http://transformunify.org/ontologies/TURBO_0000650",
                            "rdfsLabel": "shortcut health care encounter to encounter identifier registry URI string"
                        },
                        "origin": "User",
                        "confidenceScore": 1.0
                    },
                    {
                        "hNodeId": "HN1239",
                        "domain": {
                            "uri": "http://purl.obolibrary.org/obo/OGMS_0000097",
                            "rdfsLabel": "health care encounter"
                        },
                        "type": {
                            "uri": "http://transformunify.org/ontologies/TURBO_0000650",
                            "rdfsLabel": "shortcut health care encounter to encounter identifier registry URI string"
                        },
                        "origin": "User",
                        "confidenceScore": 1.0
                    }
                ],
                "learnedSemanticTypes": null,
                "modelIds": null
            },
            {
                "id": "HN12",
                "label": {
                    "uri": "HN12",
                    "rdfsLabel": null
                },
                "type": "ColumnNode",
                "hNodeId": "HN12",
                "columnName": "RAWTOHEX.FK_PATIENT_ENCOUNTER_ID.",
                "rdfLiteralType": null,
                "language": "",
                "userSemanticTypes": [
                    {
                        "hNodeId": "HN12",
                        "domain": {
                            "uri": "http://purl.obolibrary.org/obo/OGMS_0000097",
                            "rdfsLabel": "health care encounter"
                        },
                        "type": {
                            "uri": "http://transformunify.org/ontologies/TURBO_0000648",
                            "rdfsLabel": "shortcut health care encounter to encounter ID symbol"
                        },
                        "origin": "User",
                        "confidenceScore": 1.0
                    },
                    {
                        "hNodeId": "HN12",
                        "domain": {
                            "uri": "http://purl.obolibrary.org/obo/OGMS_0000097",
                            "rdfsLabel": "health care encounter"
                        },
                        "type": {
                            "uri": "http://transformunify.org/ontologies/TURBO_0000648",
                            "rdfsLabel": "shortcut health care encounter to encounter ID symbol"
                        },
                        "origin": "User",
                        "confidenceScore": 1.0
                    },
                    {
                        "hNodeId": "HN12",
                        "domain": {
                            "uri": "http://purl.obolibrary.org/obo/OGMS_0000097",
                            "rdfsLabel": "health care encounter"
                        },
                        "type": {
                            "uri": "http://transformunify.org/ontologies/TURBO_0000648",
                            "rdfsLabel": "shortcut health care encounter to encounter ID symbol"
                        },
                        "origin": "User",
                        "confidenceScore": 1.0
                    }
                ],
                "learnedSemanticTypes": null,
                "modelIds": null
            },
            {
                "id": "HN1135",
                "label": {
                    "uri": "HN1135",
                    "rdfsLabel": null
                },
                "type": "ColumnNode",
                "hNodeId": "HN1135",
                "columnName": "enc_uri",
                "rdfLiteralType": null,
                "language": "",
                "userSemanticTypes": [
                    {
                        "hNodeId": "HN1135",
                        "domain": {
                            "uri": "http://purl.obolibrary.org/obo/OGMS_0000097",
                            "rdfsLabel": "health care encounter"
                        },
                        "type": {
                            "uri": "http://isi.edu/integration/karma/dev#classLink",
                            "rdfsLabel": null
                        },
                        "origin": "User",
                        "confidenceScore": 1.0
                    },
                    {
                        "hNodeId": "HN1135",
                        "domain": {
                            "uri": "http://purl.obolibrary.org/obo/OGMS_0000097",
                            "rdfsLabel": "health care encounter"
                        },
                        "type": {
                            "uri": "http://isi.edu/integration/karma/dev#classLink",
                            "rdfsLabel": null
                        },
                        "origin": "User",
                        "confidenceScore": 1.0
                    },
                    {
                        "hNodeId": "HN1135",
                        "domain": {
                            "uri": "http://purl.obolibrary.org/obo/OGMS_0000097",
                            "rdfsLabel": "health care encounter"
                        },
                        "type": {
                            "uri": "http://isi.edu/integration/karma/dev#classLink",
                            "rdfsLabel": null
                        },
                        "origin": "User",
                        "confidenceScore": 1.0
                    }
                ],
                "learnedSemanticTypes": null,
                "modelIds": null
            },
            {
                "id": "HN14",
                "label": {
                    "uri": "HN14",
                    "rdfsLabel": null
                },
                "type": "ColumnNode",
                "hNodeId": "HN14",
                "columnName": "ORDER_NAME",
                "rdfLiteralType": null,
                "language": "",
                "userSemanticTypes": [
                    {
                        "hNodeId": "HN14",
                        "domain": {
                            "uri": "http://purl.obolibrary.org/obo/PDRO_0000024",
                            "rdfsLabel": "drug prescription"
                        },
                        "type": {
                            "uri": "http://transformunify.org/ontologies/TURBO_0005611",
                            "rdfsLabel": "shortcut prescription to prescription fullname/order_name"
                        },
                        "origin": "User",
                        "confidenceScore": 1.0
                    },
                    {
                        "hNodeId": "HN14",
                        "domain": {
                            "uri": "http://purl.obolibrary.org/obo/PDRO_0000024",
                            "rdfsLabel": "drug prescription"
                        },
                        "type": {
                            "uri": "http://transformunify.org/ontologies/TURBO_0005611",
                            "rdfsLabel": "shortcut prescription to prescription fullname/order_name"
                        },
                        "origin": "User",
                        "confidenceScore": 1.0
                    },
                    {
                        "hNodeId": "HN14",
                        "domain": {
                            "uri": "http://purl.obolibrary.org/obo/PDRO_0000024",
                            "rdfsLabel": "drug prescription"
                        },
                        "type": {
                            "uri": "http://transformunify.org/ontologies/TURBO_0005611",
                            "rdfsLabel": "shortcut prescription to prescription fullname/order_name"
                        },
                        "origin": "User",
                        "confidenceScore": 1.0
                    }
                ],
                "learnedSemanticTypes": null,
                "modelIds": null
            },
            {
                "id": "HN13",
                "label": {
                    "uri": "HN13",
                    "rdfsLabel": null
                },
                "type": "ColumnNode",
                "hNodeId": "HN13",
                "columnName": "PK_ORDER_MED_ID",
                "rdfLiteralType": null,
                "language": "",
                "userSemanticTypes": [
                    {
                        "hNodeId": "HN13",
                        "domain": {
                            "uri": "http://purl.obolibrary.org/obo/PDRO_0000024",
                            "rdfsLabel": "drug prescription"
                        },
                        "type": {
                            "uri": "http://transformunify.org/ontologies/TURBO_0005601",
                            "rdfsLabel": "shortcut prescription to prescription CRID symbol"
                        },
                        "origin": "User",
                        "confidenceScore": 1.0
                    },
                    {
                        "hNodeId": "HN13",
                        "domain": {
                            "uri": "http://purl.obolibrary.org/obo/PDRO_0000024",
                            "rdfsLabel": "drug prescription"
                        },
                        "type": {
                            "uri": "http://transformunify.org/ontologies/TURBO_0005601",
                            "rdfsLabel": "shortcut prescription to prescription CRID symbol"
                        },
                        "origin": "User",
                        "confidenceScore": 1.0
                    },
                    {
                        "hNodeId": "HN13",
                        "domain": {
                            "uri": "http://purl.obolibrary.org/obo/PDRO_0000024",
                            "rdfsLabel": "drug prescription"
                        },
                        "type": {
                            "uri": "http://transformunify.org/ontologies/TURBO_0005601",
                            "rdfsLabel": "shortcut prescription to prescription CRID symbol"
                        },
                        "origin": "User",
                        "confidenceScore": 1.0
                    }
                ],
                "learnedSemanticTypes": null,
                "modelIds": null
            },
            {
                "id": "HN1031",
                "label": {
                    "uri": "HN1031",
                    "rdfsLabel": null
                },
                "type": "ColumnNode",
                "hNodeId": "HN1031",
                "columnName": "prescription_uri",
                "rdfLiteralType": null,
                "language": "",
                "userSemanticTypes": [
                    {
                        "hNodeId": "HN1031",
                        "domain": {
                            "uri": "http://purl.obolibrary.org/obo/PDRO_0000024",
                            "rdfsLabel": "drug prescription"
                        },
                        "type": {
                            "uri": "http://isi.edu/integration/karma/dev#classLink",
                            "rdfsLabel": null
                        },
                        "origin": "User",
                        "confidenceScore": 1.0
                    },
                    {
                        "hNodeId": "HN1031",
                        "domain": {
                            "uri": "http://purl.obolibrary.org/obo/PDRO_0000024",
                            "rdfsLabel": "drug prescription"
                        },
                        "type": {
                            "uri": "http://isi.edu/integration/karma/dev#classLink",
                            "rdfsLabel": null
                        },
                        "origin": "User",
                        "confidenceScore": 1.0
                    },
                    {
                        "hNodeId": "HN1031",
                        "domain": {
                            "uri": "http://purl.obolibrary.org/obo/PDRO_0000024",
                            "rdfsLabel": "drug prescription"
                        },
                        "type": {
                            "uri": "http://isi.edu/integration/karma/dev#classLink",
                            "rdfsLabel": null
                        },
                        "origin": "User",
                        "confidenceScore": 1.0
                    }
                ],
                "learnedSemanticTypes": null,
                "modelIds": null
            },
            {
                "id": "HN17",
                "label": {
                    "uri": "HN17",
                    "rdfsLabel": null
                },
                "type": "ColumnNode",
                "hNodeId": "HN17",
                "columnName": "d.full_s",
                "rdfLiteralType": {
                    "uri": "http://www.w3.org/2001/XMLSchema#anyURI",
                    "rdfsLabel": null
                },
                "language": "",
                "userSemanticTypes": [
                    {
                        "hNodeId": "HN17",
                        "domain": {
                            "uri": "http://purl.obolibrary.org/obo/PDRO_0000024",
                            "rdfsLabel": "drug prescription"
                        },
                        "type": {
                            "uri": "http://transformunify.org/ontologies/TURBO_0005612",
                            "rdfsLabel": "shortcut prescription to drug uri string"
                        },
                        "origin": "User",
                        "confidenceScore": 1.0
                    },
                    {
                        "hNodeId": "HN17",
                        "domain": {
                            "uri": "http://purl.obolibrary.org/obo/PDRO_0000024",
                            "rdfsLabel": "drug prescription"
                        },
                        "type": {
                            "uri": "http://transformunify.org/ontologies/TURBO_0005612",
                            "rdfsLabel": "shortcut prescription to drug uri string"
                        },
                        "origin": "User",
                        "confidenceScore": 1.0
                    },
                    {
                        "hNodeId": "HN17",
                        "domain": {
                            "uri": "http://purl.obolibrary.org/obo/PDRO_0000024",
                            "rdfsLabel": "drug prescription"
                        },
                        "type": {
                            "uri": "http://transformunify.org/ontologies/TURBO_0005612",
                            "rdfsLabel": "shortcut prescription to drug uri string"
                        },
                        "origin": "User",
                        "confidenceScore": 1.0
                    }
                ],
                "learnedSemanticTypes": null,
                "modelIds": null
            },
            {
                "id": "mapped_orders.csv 20180329 via wes_pds_enc__med_order.csv1",
                "label": {
                    "uri": "",
                    "rdfsLabel": null
                },
                "type": "LiteralNode",
                "value": "mapped_orders.csv 20180329 via wes_pds_enc__med_order.csv",
                "datatype": {
                    "uri": "",
                    "rdfsLabel": null
                },
                "language": "",
                "isUri": "false",
                "modelIds": null
            }
        ],
        "links": [
            {
                "id": "http://purl.obolibrary.org/obo/OGMS_00000971---http://purl.obolibrary.org/obo/RO_0002234---http://purl.obolibrary.org/obo/PDRO_00000241",
                "weight": 0.009999999776482582,
                "type": "ObjectPropertyLink",
                "label": {
                    "uri": "http://purl.obolibrary.org/obo/RO_0002234",
                    "rdfsLabel": "has output"
                },
                "objectPropertyType": "WithoutDomainAndRange",
                "status": "ForcedByUser",
                "keyInfo": "None",
                "modelIds": null
            },
            {
                "id": "http://purl.obolibrary.org/obo/OGMS_00000971---http://transformunify.org/ontologies/TURBO_0000650---HN1239",
                "weight": 0.01,
                "type": "DataPropertyLink",
                "label": {
                    "uri": "http://transformunify.org/ontologies/TURBO_0000650",
                    "rdfsLabel": "shortcut health care encounter to encounter identifier registry URI string"
                },
                "status": "ForcedByUser",
                "keyInfo": "None",
                "modelIds": null
            },
            {
                "id": "http://purl.obolibrary.org/obo/OGMS_00000971---http://transformunify.org/ontologies/TURBO_0000648---HN12",
                "weight": 0.01,
                "type": "DataPropertyLink",
                "label": {
                    "uri": "http://transformunify.org/ontologies/TURBO_0000648",
                    "rdfsLabel": "shortcut health care encounter to encounter ID symbol"
                },
                "status": "ForcedByUser",
                "keyInfo": "None",
                "modelIds": null
            },
            {
                "id": "http://purl.obolibrary.org/obo/OGMS_00000971---http://isi.edu/integration/karma/dev#classLink---HN1135",
                "weight": 0.01,
                "type": "ClassInstanceLink",
                "label": {
                    "uri": "http://isi.edu/integration/karma/dev#classLink",
                    "rdfsLabel": null
                },
                "status": "ForcedByUser",
                "keyInfo": "UriOfInstance",
                "modelIds": null
            },
            {
                "id": "http://purl.obolibrary.org/obo/PDRO_00000241---http://transformunify.org/ontologies/TURBO_0005611---HN14",
                "weight": 0.01,
                "type": "DataPropertyLink",
                "label": {
                    "uri": "http://transformunify.org/ontologies/TURBO_0005611",
                    "rdfsLabel": "shortcut prescription to prescription fullname/order_name"
                },
                "status": "ForcedByUser",
                "keyInfo": "None",
                "modelIds": null
            },
            {
                "id": "http://purl.obolibrary.org/obo/PDRO_00000241---http://transformunify.org/ontologies/TURBO_0005601---HN13",
                "weight": 0.01,
                "type": "DataPropertyLink",
                "label": {
                    "uri": "http://transformunify.org/ontologies/TURBO_0005601",
                    "rdfsLabel": "shortcut prescription to prescription CRID symbol"
                },
                "status": "ForcedByUser",
                "keyInfo": "None",
                "modelIds": null
            },
            {
                "id": "http://purl.obolibrary.org/obo/PDRO_00000241---http://isi.edu/integration/karma/dev#classLink---HN1031",
                "weight": 0.01,
                "type": "ClassInstanceLink",
                "label": {
                    "uri": "http://isi.edu/integration/karma/dev#classLink",
                    "rdfsLabel": null
                },
                "status": "ForcedByUser",
                "keyInfo": "UriOfInstance",
                "modelIds": null
            },
            {
                "id": "http://purl.obolibrary.org/obo/PDRO_00000241---http://transformunify.org/ontologies/TURBO_0005612---HN17",
                "weight": 0.01,
                "type": "DataPropertyLink",
                "label": {
                    "uri": "http://transformunify.org/ontologies/TURBO_0005612",
                    "rdfsLabel": "shortcut prescription to drug uri string"
                },
                "status": "ForcedByUser",
                "keyInfo": "None",
                "modelIds": null
            },
            {
                "id": "http://purl.obolibrary.org/obo/OGMS_00000971---http://transformunify.org/ontologies/TURBO_0000643---mapped_orders.csv 20180329 via wes_pds_enc__med_order.csv1",
                "weight": 0.01,
                "type": "ObjectPropertyLink",
                "label": {
                    "uri": "http://transformunify.org/ontologies/TURBO_0000643",
                    "rdfsLabel": "shortcut health care encounter to data set title"
                },
                "objectPropertyType": "None",
                "status": "ForcedByUser",
                "keyInfo": "None",
                "modelIds": null
            }
        ]
    }
}